.gitignore
LICENSE
MANIFEST.in
README.rst
requirements.txt
runtests.py
setup.py
privileges/__init__.py
privileges/admin.py
privileges/auth_backends.py
privileges/decorators.py
privileges/forms.py
privileges/grants.py
privileges/models.py
privileges/registration.py
privileges/urls.py
privileges/views.py
privileges.egg-info/PKG-INFO
privileges.egg-info/SOURCES.txt
privileges.egg-info/dependency_links.txt
privileges.egg-info/not-zip-safe
privileges.egg-info/top_level.txt
privileges/templates/privileges/base.html
privileges/templates/privileges/grant_confirm_delete.html
privileges/templates/privileges/grant_form.html
privileges/templates/privileges/grant_list.html
privileges/templatetags/__init__.py
privileges/templatetags/privileges_tags.py